onixcheck/__init__.py
onixcheck/__main__.py
onixcheck/exeptions.py
onixcheck/models.py
onixcheck/onixfix.py
onixcheck/utils.py
onixcheck/validation.py
onixcheck/data/Google Sample ONIX 2.1.xml
onixcheck/data/__init__.py
onixcheck/data/invalid_google_onix_3.xml
onixcheck/data/invalid_onix3_ref.xml
onixcheck/data/invalid_onix_root.xml
onixcheck/data/valid_google_onix_3.xml
onixcheck/data/valid_onix2_ref.xml
onixcheck/data/valid_onix31_ref.xml
onixcheck/data/valid_onix31_short.xml
onixcheck/data/valid_onix3_ref.xml
onixcheck/data/valid_onix3_ref_ns.xml
onixcheck/data/valid_onix3_short.xml
onixcheck/data/win_console_issue.xml
onixcheck/schema/__init__.py
onixcheck/schema/biblon/biblon_2.1.yaml
onixcheck/schema/biblon/biblon_onix_30.rng
onixcheck/schema/biblon/biblon_onix_30.yaml
onixcheck/schema/google/google_onix_30.yaml
onixcheck/schema/rng3.0/ONIX_BookProduct_3.0_reference.rng
onixcheck/schema/rng3.0/ONIX_BookProduct_3.0_short.rng
onixcheck/schema/rng3.0/ONIX_BookProduct_CodeLists.rng
onixcheck/schema/rng3.0/ONIX_XHTML_Subset.rng
onixcheck/schema/rng3.1/ONIX_BookProduct_3.1_reference.rng
onixcheck/schema/rng3.1/ONIX_BookProduct_3.1_short.rng
onixcheck/schema/rng3.1/ONIX_BookProduct_CodeLists.rng
onixcheck/schema/rng3.1/ONIX_XHTML_Subset.rng
onixcheck/schema/xsd2.1/ONIX_BookProduct_CodeLists.xsd
onixcheck/schema/xsd2.1/ONIX_BookProduct_Release2.1_reference.xsd
onixcheck/schema/xsd2.1/ONIX_BookProduct_Release2.1_short.xsd
onixcheck/schema/xsd2.1/ONIX_XHTML_Subset.xsd
onixcheck/schema/xsd2.1/ONIX_XHTML_Subset_reference.xsd
onixcheck/schema/xsd2.1/ONIX_XHTML_Subset_short.xsd
onixcheck/schema/xsd3.0/ONIX_BookProduct_3.0_reference.xsd
onixcheck/schema/xsd3.0/ONIX_BookProduct_3.0_short.xsd
onixcheck/schema/xsd3.0/ONIX_BookProduct_CodeLists.xsd
onixcheck/schema/xsd3.0/ONIX_XHTML_Subset.xsd
onixcheck/schema/xsd3.1/ONIX_BookProduct_3.1_reference.xsd
onixcheck/schema/xsd3.1/ONIX_BookProduct_3.1_short.xsd
onixcheck/schema/xsd3.1/ONIX_BookProduct_CodeLists.xsd
onixcheck-0.9.10.dist-info/METADATA
onixcheck-0.9.10.dist-info/WHEEL
onixcheck-0.9.10.dist-info/entry_points.txt
onixcheck-0.9.10.dist-info/licenses/AUTHORS.md
onixcheck-0.9.10.dist-info/licenses/LICENSE
onixcheck-0.9.10.dist-info/RECORD
