Metadata-Version: 2.4
Name: onixcheck
Version: 0.9.10
Summary: ONIX validation library and commandline tool
Project-URL: Homepage, https://github.com/titusz/onixcheck
Project-URL: Repository, https://github.com/titusz/onixcheck
Author-email: Titusz Pan <tp@py7.de>
License-Expression: Apache-2.0
License-File: AUTHORS.md
License-File: LICENSE
Keywords: EDItEUR,ONIX,RelaxNG,XML,XMLSchema,validation
Classifier: Development Status :: 5 - Production/Stable
Classifier: Intended Audience :: Developers
Classifier: License :: OSI Approved :: BSD License
Classifier: Operating System :: Microsoft :: Windows
Classifier: Operating System :: POSIX
Classifier: Operating System :: Unix
Classifier: Programming Language :: Python
Classifier: Programming Language :: Python :: 3
Classifier: Topic :: Utilities
Requires-Python: >=3.9
Requires-Dist: defusedxml
Requires-Dist: isbnlib
Requires-Dist: lxml
Requires-Dist: pyyaml
Requires-Dist: six
Requires-Dist: win-unicode-console; platform_system == 'Windows'
